[
  {
    "localization": {
      "de": {
        "urls": [],
        "text": {
          "title": "Wundersch\u00f6ne Studio nah an der Aare",
          "description": "Hier gibt es eine Wundersch\u00f6ne Wohnung f\u00fcr 6 Monaten zum Untermieten. Die Wohnung liegt 5 Minuten zu Fuss von der Zytggloge entfernt. Das Quartiert ist sehr ruhig und die Aare ist sehr nah. Die Wohnung steht im EG mit einem grossen Garten. Die Wohnung ist M\u00f6bliert. <br />Mietzeit: Von 0 1.0 1.2024 - 3 1.06.2024 oder nach Vereinbarung."
        },
        "attachments": [
          {
            "type": "IMAGE",
            "url": "https://media2.homegate.ch/listings/v2/tuttifill/4000269209/image/dc9c3db6460f3c1457add5a42f67e347.jpg",
            "file": "tutti_bf80186656b1c2e9b931bf405c3452d2.jpg"
          },
          {
            "type": "IMAGE",
            "url": "https://media2.homegate.ch/listings/v2/tuttifill/4000269209/image/aeacf7d7d7fabbb498b57a96907f5b29.jpg",
            "file": "tutti_cef7bf8df7cb17b21bbbdb6b3a0c7d9e.jpg"
          },
          {
            "type": "IMAGE",
            "url": "https://media2.homegate.ch/listings/v2/tuttifill/4000269209/image/a384ca98f8d3181a928a165481b0d98d.jpg",
            "file": "tutti_4a7f4d82fb342ff362a0ba890bbe7c03.jpg"
          },
          {
            "type": "IMAGE",
            "url": "https://media2.homegate.ch/listings/v2/tuttifill/4000269209/image/5efc934fd15635182b050454a939b8a7.jpg",
            "file": "tutti_2b1003d25abe397283e57d227f951c44.jpg"
          },
          {
            "type": "IMAGE",
            "url": "https://media2.homegate.ch/listings/v2/tuttifill/4000269209/image/cf1a0b2375c1d92181bd6111e090b41d.jpg",
            "file": "tutti_24273421432273f7c15abf603c5b9468.jpg"
          }
        ]
      },
      "primary": "de"
    },
    "lister": {
      "legalName": "Vasudeva",
      "website": {
        "value": "https://www.tutti.ch"
      },
      "id": "tuttifill",
      "contacts": {
        "inquiry": {},
        "viewing": {}
      },
      "allowToContact": false
    },
    "characteristics": {
      "livingSpace": 41,
      "numberOfRooms": 1
    },
    "address": {
      "country": "CH",
      "geoDistances": [
        {
          "distance": -10388.31841047525,
          "geoTag": "geo-canton-bern"
        },
        {
          "distance": -1630.4206584556755,
          "geoTag": "geo-city-bern"
        },
        {
          "distance": -25.65459540747564,
          "geoTag": "geo-citydistrict-spitalacker"
        },
        {
          "distance": -381.384373064381,
          "geoTag": "geo-cityregion-breitenrain-lorraine"
        },
        {
          "distance": -49071.31884307248,
          "geoTag": "geo-country-switzerland"
        },
        {
          "distance": -1630.4206584556755,
          "geoTag": "geo-region-bern"
        },
        {
          "distance": -6713.433647590513,
          "geoTag": "geo-region-bern-mittelland"
        },
        {
          "distance": -1630.4206584556755,
          "geoTag": "geo-zipcode-3000"
        },
        {
          "distance": -332.83439266090625,
          "geoTag": "geo-zipcode-3013"
        }
      ],
      "geoTags": [
        "geo-canton-bern",
        "geo-city-bern",
        "geo-citydistrict-spitalacker",
        "geo-cityregion-breitenrain-lorraine",
        "geo-country-switzerland",
        "geo-region-bern",
        "geo-region-bern-mittelland",
        "geo-zipcode-3000",
        "geo-zipcode-3013"
      ],
      "street": "Altenberg",
      "postalCode": "3013",
      "locality": "Bern",
      "geoCoordinates": {
        "accuracy": "HIGH",
        "manual": false,
        "latitude": 46.955141562119,
        "longitude": 7.446921501257
      }
    },
    "externalIds": {
      "internalReferenceId": "tuttifill#63014477##",
      "displayReferenceId": "63014477",
      "refObject": "63014477",
      "displayPropertyReferenceId": "63014477",
      "propertyReferenceId": "tuttifill#63014477##"
    },
    "contactForm": {
      "size": "NO_ADDRESS",
      "deliveryFormat": "NORMAL"
    },
    "version": 1,
    "platforms": [
      "homegate",
      "alleimmobilien",
      "home",
      "immostreet"
    ],
    "offerType": "RENT",
    "meta": {
      "createdAt": "2023-10-26T07:17:48.108Z",
      "updatedAt": "2023-10-27T07:16:58.050Z",
      "source": "FILSINGER"
    },
    "id": "4000269209",
    "categories": [
      "APARTMENT",
      "FLAT"
    ],
    "prices": {
      "rent": {
        "area": "ALL",
        "interval": "MONTH",
        "gross": 1520
      },
      "currency": "CHF"
    },
    "valueAddedServices": {
      "isTenantPlusListing": true
    }
  }
]