[
  {
    "text": "Why do u have them",
    "comment_language": "en",
    "digg_count": 3252,
    "reply_comment_total": 10,
    "author_pin": false,
    "create_time": 1676080038,
    "cid": "7198708872234664710",
    "nickname": "jordan.wav",
    "unique_id": "jordan.wav",
    "aweme_id": "7198206283571285294"
  },
  {
    "text": "what about human",
    "comment_language": "en",
    "digg_count": 111,
    "reply_comment_total": 2,
    "author_pin": false,
    "create_time": 1676296559,
    "cid": "7199638782328587010",
    "nickname": "Matthew fredericks",
    "unique_id": "matthewfredericks.26",
    "aweme_id": "7198206283571285294"
  },
  {
    "text": "where are you buying this",
    "comment_language": "en",
    "digg_count": 1,
    "reply_comment_total": 0,
    "author_pin": false,
    "create_time": 1680678501,
    "cid": "7218459089193386753",
    "nickname": "Zac",
    "unique_id": "zacturnher",
    "aweme_id": "7198206283571285294"
  },
  {
    "text": "Why do you have these in ur house? And where do you even get them?",
    "comment_language": "en",
    "digg_count": 1,
    "reply_comment_total": 0,
    "author_pin": false,
    "create_time": 1737938543,
    "cid": "7464389098343564078",
    "nickname": "lol",
    "unique_id": "ngl_its_jr_boi",
    "aweme_id": "7198206283571285294"
  },
  {
    "text": "M. Hmza",
    "comment_language": "id",
    "digg_count": 65,
    "reply_comment_total": 0,
    "author_pin": false,
    "create_time": 1677671881,
    "cid": "7205545733238489899",
    "nickname": "Chrislimax",
    "unique_id": "chrislimax",
    "aweme_id": "7198206283571285294"
  },
  {
    "text": "i havo one of those in the back",
    "comment_language": "en",
    "digg_count": 92,
    "reply_comment_total": 0,
    "author_pin": false,
    "create_time": 1675970196,
    "cid": "7198237101288211206",
    "nickname": "Ron Bill Weasley",
    "unique_id": "ronbillweasley",
    "aweme_id": "7198206283571285294"
  },
  {
    "text": "Someone told bro to get a backbone and he took it serious 💀",
    "comment_language": "en",
    "digg_count": 109,
    "reply_comment_total": 0,
    "author_pin": false,
    "create_time": 1676033682,
    "cid": "7198509704762311470",
    "nickname": "Castor-Troy",
    "unique_id": "that_funny_axolotl",
    "aweme_id": "7198206283571285294"
  },
  {
    "text": "thank you waldo",
    "comment_language": "en",
    "digg_count": 44,
    "reply_comment_total": 0,
    "author_pin": false,
    "create_time": 1675978166,
    "cid": "7198271360630555438",
    "nickname": "Rain",
    "unique_id": "rainbz",
    "aweme_id": "7198206283571285294"
  },
  {
    "text": "WALDO",
    "comment_language": "en",
    "digg_count": 46,
    "reply_comment_total": 0,
    "author_pin": false,
    "create_time": 1683595285,
    "cid": "7230986647205249835",
    "nickname": "HolaNinnerss",
    "unique_id": "jamrurpf0vm",
    "aweme_id": "7198206283571285294"
  },
  {
    "text": "I watched you in my science class fifth grade😂",
    "comment_language": "en",
    "digg_count": 69,
    "reply_comment_total": 0,
    "author_pin": false,
    "create_time": 1681650927,
    "cid": "7222635563196351278",
    "nickname": "IIshow_Isaac🙄💵💰🤡",
    "unique_id": "iishow_isaac",
    "aweme_id": "7198206283571285294"
  },
  {
    "text": "Bro is that sup 1880 or where’s Waldo",
    "comment_language": "en",
    "digg_count": 58,
    "reply_comment_total": 0,
    "author_pin": false,
    "create_time": 1681520568,
    "cid": "7222075806250435370",
    "nickname": "A bozo",
    "unique_id": "ealum_fortyfou.r",
    "aweme_id": "7198206283571285294"
  },
  {
    "text": "EY ITS WALDO",
    "comment_language": "de",
    "digg_count": 33,
    "reply_comment_total": 0,
    "author_pin": false,
    "create_time": 1675978145,
    "cid": "7198271261704110894",
    "nickname": "Beef",
    "unique_id": "timekeepercookiex",
    "aweme_id": "7198206283571285294"
  },
  {
    "text": "Can u do skull",
    "comment_language": "en",
    "digg_count": 59,
    "reply_comment_total": 0,
    "author_pin": false,
    "create_time": 1679529477,
    "cid": "7213524138147791658",
    "nickname": "⠀ ⠀ ⠀ ⠀ ⠀",
    "unique_id": "c4ts.are.coool",
    "aweme_id": "7198206283571285294"
  },
  {
    "text": "why the hell do you have so many backbones",
    "comment_language": "en",
    "digg_count": 69,
    "reply_comment_total": 0,
    "author_pin": false,
    "create_time": 1677398831,
    "cid": "7204372995320709934",
    "nickname": "09kingofthecourt",
    "unique_id": "09kingofthecourt",
    "aweme_id": "7198206283571285294"
  },
  {
    "text": "why does he think we know the average size of a where's waldo figure",
    "comment_language": "en",
    "digg_count": 85,
    "reply_comment_total": 0,
    "author_pin": false,
    "create_time": 1675974121,
    "cid": "7198253968039019306",
    "nickname": "*__*",
    "unique_id": "3333e_e",
    "aweme_id": "7198206283571285294"
  },
  {
    "text": "oh i thought you would say \"your mum\" or something",
    "comment_language": "en",
    "digg_count": 62,
    "reply_comment_total": 0,
    "author_pin": false,
    "create_time": 1676150770,
    "cid": "7199012413043442434",
    "nickname": "net slov tol'ko hooy",
    "unique_id": "mr.no_fase",
    "aweme_id": "7198206283571285294"
  },
  {
    "text": "wow",
    "comment_language": "en",
    "digg_count": 41,
    "reply_comment_total": 0,
    "author_pin": false,
    "create_time": 1707896234,
    "cid": "7335358287985050414",
    "nickname": "Moses | ∀Γ∀φ(Γ ⊨ φ → Γ ⊢ φ)",
    "unique_id": "iammoses238",
    "aweme_id": "7198206283571285294"
  },
  {
    "text": "FOUND IT",
    "comment_language": "en",
    "digg_count": 62,
    "reply_comment_total": 0,
    "author_pin": false,
    "create_time": 1679114887,
    "cid": "7211743410096833323",
    "nickname": "Eddie <3",
    "unique_id": "_ed_die_",
    "aweme_id": "7198206283571285294"
  },
  {
    "text": "hey i was using those!!!",
    "comment_language": "en",
    "digg_count": 70,
    "reply_comment_total": 0,
    "author_pin": false,
    "create_time": 1679629909,
    "cid": "7213955456040551210",
    "nickname": "mars!! 🔑🌙 (real #1 leon fan)",
    "unique_id": "no.1leonkennedykisser",
    "aweme_id": "7198206283571285294"
  },
  {
    "text": "squrtle",
    "comment_language": "en",
    "digg_count": 44,
    "reply_comment_total": 0,
    "author_pin": false,
    "create_time": 1706100619,
    "cid": "7327646178804761390",
    "nickname": "Purple Dude",
    "unique_id": "purple_dude1983",
    "aweme_id": "7198206283571285294"
  }
]