{
  "id": "3111290796599140206",
  "shortcode": "Csthn7EO99u",
  "dimensions": {
    "height": 1080,
    "width": 1080
  },
  "src": "https://scontent-sea1-1.cdninstagram.com/v/t51.29350-15/349039099_963489458180161_6331225178943966048_n.webp?stp=dst-jpg_e35&_nc_ht=scontent-sea1-1.cdninstagram.com&_nc_cat=101&_nc_ohc=f9bihcdjG9gQ7kNvgFVrO61&edm=AP_V10EBAAAA&ccb=7-5&oh=00_AYDsoXm5kmIP1RMtKlwXS9WVEA_siT570c_3o5eEi5bKWg&oe=66B92196&_nc_sid=2999b8",
  "thumbnail_src": null,
  "media_preview": null,
  "video_url": null,
  "views": null,
  "likes": 7767,
  "location": null,
  "taken_at": 1685114787,
  "related": [],
  "type": null,
  "video_duration": null,
  "music": null,
  "is_video": false,
  "tagged_users": [],
  "captions": [
    "Starting today, you can experiment with generative AI in Search. Opt in by tapping the Labs icon on the latest versions of your Google app or desktop Chrome browser or join the waitlist at labs.google.com/search. Once you’re in, the new generative AI-powered Search experience will help make your next search simpler - like when you need to easily get up to speed on a new or complicated topic, uncover quick tips for your specific questions or discover a range of products when shopping. \n\nTap the link in our bio to learn more, and swipe through for tips on how to get started."
  ],
  "related_profiles": [
    "googlefordevs",
    "android",
    "googledeepmind",
    "pixar",
    "bugatti",
    "duolingo",
    "mrwhosetheboss",
    "disney",
    "nothing",
    "googlemaps",
    "sony",
    "vancityreynolds",
    "nvidiageforce",
    "ezsnippet",
    "lego",
    "spotify",
    "ferrari",
    "9gag",
    "asusrog",
    "thestevenhe",
    "razer",
    "mit",
    "figma",
    "imparkerburton",
    "koenigsegg",
    "appledsign",
    "markrober",
    "iss",
    "sundarpichai",
    "roblox",
    "thevarunmayya",
    "omaragamyy",
    "marvel_india",
    "asus",
    "ubisoft",
    "microsoft365",
    "interestingengineering",
    "kirkiimad",
    "wwwchesscom",
    "433",
    "beebomco",
    "evancronin_",
    "maserati",
    "dell",
    "sachintendulkar",
    "voguemagazine",
    "mancity",
    "dhruvrathee",
    "tiboinshape",
    "bhuvan.bam22",
    "lukedavidson__",
    "lalalalisa_m",
    "igndotcom",
    "fallontonight",
    "premierleague",
    "milliebobbybrown",
    "aliaabhatt",
    "sabrinacarpenter",
    "neymarjr",
    "billboard",
    "fuckboyproblem.s",
    "jordan_the_stallion8",
    "louisvuitton",
    "crawly_goat",
    "coldplay",
    "nba",
    "microsoftidc",
    "yong.lixx",
    "hynjinnnn",
    "oliviarodrigo",
    "threads",
    "sonyxperia",
    "katyperry",
    "miniverse.___",
    "_doolsetnet",
    "jutdwae",
    "digitaltrends",
    "arshgoyalyt",
    "nvidiaai",
    "corsair"
  ],
  "comments_count": 132,
  "comments_disabled": false,
  "comments_next_page": "{\"server_cursor\": \"QVFCTnRTVzh0Z3ZVV0VNM29IWnBpenJ2eGQydzNPcjA1LWdhelhDQjJpWXVJcDAxd1U4ajRvM3BTN0I0eFJiZnNmZGRyZ1BQckdUeW4tY3VlWUVXSlRJeg==\", \"is_server_cursor_inverse\": true}",
  "comments": [
    {
      "id": "17988851905979218",
      "text": "eb_s_20",
      "created_at": 1688346631,
      "owner": "bbmmn231",
      "owner_verified": false,
      "viewer_has_liked": false,
      "likes": 0
    },
    {
      "id": "18340648084074792",
      "text": "Insightful 👏",
      "created_at": 1686948369,
      "owner": "m_t_y_space",
      "owner_verified": false,
      "viewer_has_liked": false,
      "likes": 0
    },
    {
      "id": "17978977775257684",
      "text": "Please follow https://instagram.com/graphics_with_fatima?igshid=MzRlODBiNWFlZA==",
      "created_at": 1686379541,
      "owner": "_fatima_.habib",
      "owner_verified": false,
      "viewer_has_liked": false,
      "likes": 0
    },
    {
      "id": "18068259685382850",
      "text": "😂Google et ses faux avis qu'on ne peut pas supprimer malgré les réclamations....😂",
      "created_at": 1686030194,
      "owner": "nosybeimports",
      "owner_verified": false,
      "viewer_has_liked": false,
      "likes": 0
    }
  ]
}